extract_monster/__init__.py
extract_monster/client.py
extract_monster/exceptions.py
extract_monster/models.py
extract_monster/py.typed
extract_monster/schemas.py
extract_monster-0.1.0.dist-info/licenses/LICENSE
extract_monster-0.1.0.dist-info/METADATA
extract_monster-0.1.0.dist-info/WHEEL
extract_monster-0.1.0.dist-info/top_level.txt
extract_monster-0.1.0.dist-info/RECORD
