Metadata-Version: 2.4
Name: extract-monster
Version: 0.1.0
Summary: Python SDK for Extract Monster - Extract structured data from files and text using AI
Author-email: Extract Monster <support@extract.monster>
Maintainer-email: Extract Monster <support@extract.monster>
License: MIT
Project-URL: Homepage, https://extract.monster
Project-URL: Documentation, https://docs.extract.monster
Project-URL: Repository, https://github.com/extract-monster/extract-monster-python
Project-URL: Bug Tracker, https://github.com/extract-monster/extract-monster-python/issues
Keywords: extract,ai,ocr,document-processing,data-extraction,pdf,invoice,receipt,gemini,structured-data
Classifier: Development Status :: 4 - Beta
Classifier: Intended Audience :: Developers
Classifier: License :: OSI Approved :: MIT License
Classifier: Operating System :: OS Independent
Classifier: Programming Language :: Python :: 3
Classifier: Programming Language :: Python :: 3.9
Classifier: Programming Language :: Python :: 3.10
Classifier: Programming Language :: Python :: 3.11
Classifier: Programming Language :: Python :: 3.12
Classifier: Programming Language :: Python :: 3.13
Classifier: Topic :: Software Development :: Libraries :: Python Modules
Classifier: Topic :: Text Processing :: General
Classifier: Topic :: Scientific/Engineering :: Artificial Intelligence
Requires-Python: >=3.9
License-File: LICENSE
Requires-Dist: httpx>=0.24.0
Provides-Extra: pydantic
Requires-Dist: pydantic>=1.10.0; extra == "pydantic"
Provides-Extra: dev
Requires-Dist: pytest>=7.0.0; extra == "dev"
Requires-Dist: pytest-cov>=4.0.0; extra == "dev"
Requires-Dist: black>=23.0.0; extra == "dev"
Requires-Dist: ruff>=0.1.0; extra == "dev"
Requires-Dist: mypy>=1.0.0; extra == "dev"
Requires-Dist: pydantic>=1.10.0; extra == "dev"
Dynamic: license-file
